mock_book_hotel/__init__.py
mock_book_hotel/fastmcp_mock_test.py
mock_book_hotel-0.1.5.dist-info/METADATA
mock_book_hotel-0.1.5.dist-info/WHEEL
mock_book_hotel-0.1.5.dist-info/entry_points.txt
mock_book_hotel-0.1.5.dist-info/RECORD
