Metadata-Version: 2.4
Name: mock-book-hotel
Version: 0.1.5
Summary: Add your description here
Author-email: yanxingyang <yanxingyang@gmail.com>
Requires-Python: >=3.11
Requires-Dist: mcp>=1.6.0
